tomo_detect/__init__.py
tomo_detect/cli.py
tomo_detect/inference.py
tomo_detect/models_manager.py
tomo_detect/models_manifest.json
tomo_detect/postprocess.py
tomo_detect/utils.py
tomo_detect/visualizations.py
tomo_detect-0.1.7.dist-info/METADATA
tomo_detect-0.1.7.dist-info/WHEEL
tomo_detect-0.1.7.dist-info/entry_points.txt
tomo_detect-0.1.7.dist-info/top_level.txt
tomo_detect-0.1.7.dist-info/RECORD
