Metadata-Version: 2.4
Name: tomo-detect
Version: 0.1.7
Summary: A CLI tool for detecting flagellar motor coordinates in tomography data
Home-page: https://github.com/Rajathk6/tomo-detect-cli
Author: Rajath Kumar
Author-email: 1rajathkumar@gmail.com
Keywords: Bacterial Flagellar Motor,tomography,motor detection,deep learning,CNN
Classifier: Development Status :: 3 - Alpha
Classifier: Intended Audience :: Science/Research
Classifier: Topic :: Scientific/Engineering :: Image Recognition
Classifier: License :: OSI Approved :: MIT License
Classifier: Programming Language :: Python :: 3.8
Classifier: Programming Language :: Python :: 3.9
Classifier: Programming Language :: Python :: 3.10
Requires-Python: >=3.8
Requires-Dist: torch>=2.0.0
Requires-Dist: numpy>=1.21.0
Requires-Dist: pandas>=1.3.0
Requires-Dist: tqdm>=4.62.0
Requires-Dist: monai>=1.0.0
Requires-Dist: mrcfile>=1.4.0
Requires-Dist: psutil>=5.8.0
Requires-Dist: rich>=10.0.0
Requires-Dist: scipy>=1.9.0
Requires-Dist: scikit-image>=0.19.0
Requires-Dist: Pillow>=9.0.0
Requires-Dist: matplotlib>=3.5.0
Requires-Dist: seaborn>=0.12.0
Dynamic: author
Dynamic: author-email
Dynamic: classifier
Dynamic: description
Dynamic: description-content-type
Dynamic: home-page
Dynamic: keywords
Dynamic: requires-dist
Dynamic: requires-python
Dynamic: summary
